{
    "id": 17,
    "row": 13,
    "col": 4,
    "title": "学生食堂",
    "text": "",
    "images": [
        "/assets/17/图片118.gif",
        "/assets/17/图片117.jpg",
        "/assets/17/图片103.jpg",
        "/assets/17/图片101.jpg",
        "/assets/17/图片110.jpg",
        "/assets/17/图片104.jpg",
        "/assets/17/图片111.jpg",
        "/assets/17/图片107.jpg",
        "/assets/17/图片106.jpg",
        "/assets/17/图片123.jpg",
        "/assets/17/图片122.jpg",
        "/assets/17/图片108.jpg",
        "/assets/17/图片120.jpg",
        "/assets/17/图片121.jpg",
        "/assets/17/图片109.jpg",
        "/assets/17/图片102 拷贝.jpg",
        "/assets/17/图片119.jpg",
        "/assets/17/图片102.gif"
    ],
    "audio": "",
    "video": ""
}